ontologise/utils.py
ontologise-0.2.1.dist-info/LICENSE
ontologise-0.2.1.dist-info/METADATA
ontologise-0.2.1.dist-info/WHEEL
ontologise-0.2.1.dist-info/top_level.txt
ontologise-0.2.1.dist-info/RECORD
