Metadata-Version: 2.1
Name: ontologise
Version: 0.2.1
Summary: Code to leverage insight from marked up historical sources
Author-email: Lisa Hopcroft <LisaEMHopcroft@gmail.com>, Michael Hopcroft <Michael.Hopcroft@gmail.com>
Project-URL: Homepage, https://github.com/LisaHopcroft/ontologise
Project-URL: Issues, https://github.com/LisaHopcroft/ontologise/issues
Classifier: Programming Language :: Python :: 3
Classifier: License :: OSI Approved :: MIT License
Classifier: Operating System :: OS Independent
Requires-Python: >=3.8
License-File: LICENSE
